netopia_sdk/__init__.py
netopia_sdk/client.py
netopia_sdk/config.py
netopia_sdk/constants.py
netopia_sdk/errors.py
netopia_sdk/ipn.py
netopia_sdk/logger.py
netopia_sdk/payment.py
netopia_sdk/transport.py
netopia_sdk/requests/__init__.py
netopia_sdk/requests/models.py
netopia_sdk/responses/__init__.py
netopia_sdk/responses/models.py
netopia_sdk-2.1.1.dist-info/licenses/LICENSE
tests/__init__.py
tests/test_client.py
tests/test_config.py
tests/test_ipn.py
netopia_sdk-2.1.1.dist-info/METADATA
netopia_sdk-2.1.1.dist-info/WHEEL
netopia_sdk-2.1.1.dist-info/top_level.txt
netopia_sdk-2.1.1.dist-info/RECORD
