Metadata-Version: 2.4
Name: netopia-sdk
Version: 2.1.1
Summary: NETOPIA Payments Python SDK for integration with the NETOPIA Payments API v2.
Home-page: https://github.com/netopiapayments/python-sdk
Author: NETOPIA Payments
Author-email: support@netopia.ro
Classifier: Programming Language :: Python :: 3
Classifier: License :: OSI Approved :: MIT License
Classifier: Operating System :: OS Independent
Requires-Python: >=3.7
License-File: LICENSE
Requires-Dist: requests>=2.28.0
Requires-Dist: pyjwt>=2.6.0
Requires-Dist: cryptography>=39.0.0
Dynamic: author
Dynamic: author-email
Dynamic: classifier
Dynamic: description
Dynamic: description-content-type
Dynamic: home-page
Dynamic: license-file
Dynamic: requires-dist
Dynamic: requires-python
Dynamic: summary
